human_short_code/__init__.py
human_short_code/core.py
human_short_code-1.0.2.dist-info/licenses/LICENSE
human_short_code-1.0.2.dist-info/METADATA
human_short_code-1.0.2.dist-info/WHEEL
human_short_code-1.0.2.dist-info/top_level.txt
human_short_code-1.0.2.dist-info/RECORD
