Metadata-Version: 2.4
Name: human-short-code
Version: 1.0.2
Summary: Replace long, unreadable ids with short human-readable code ids
Home-page: https://github.com/deadsmond/HumanShortCode
Author: Adam Lewicki
Classifier: Programming Language :: Python :: 3
Classifier: License :: OSI Approved :: MIT License
Requires-Python: >=3.6
License-File: LICENSE
Dynamic: author
Dynamic: classifier
Dynamic: description
Dynamic: description-content-type
Dynamic: home-page
Dynamic: license-file
Dynamic: requires-python
Dynamic: summary
